rahulscripts/__init__.py
rahulscripts/rahulscripts.py
rahulscripts/download/__init__.py
rahulscripts/download/downloader.py
rahulscripts/external/__init__.py
rahulscripts/external/umi_run.py
rahulscripts/metrics/__init__.py
rahulscripts/metrics/custom_metrics.py
rahulscripts/utils/__init__.py
rahulscripts/utils/text_highlight.py
rahulscripts/utils/utilities.py
RahulScripts-0.0.4.dist-info/LICENSE
RahulScripts-0.0.4.dist-info/METADATA
RahulScripts-0.0.4.dist-info/WHEEL
RahulScripts-0.0.4.dist-info/top_level.txt
RahulScripts-0.0.4.dist-info/RECORD
